AWSLibrary/__init__.py
AWSLibrary/version.py
AWSLibrary/base/__init__.py
AWSLibrary/base/exceptions.py
AWSLibrary/base/librarycomponent.py
AWSLibrary/base/robotlibcore.py
AWSLibrary/keywords/__init__.py
AWSLibrary/keywords/dynamo.py
AWSLibrary/keywords/rds.py
AWSLibrary/keywords/resource.py
AWSLibrary/keywords/s3.py
AWSLibrary/keywords/session.py
robotframework_aws-0.0.4.dist-info/LICENSE
robotframework_aws-0.0.4.dist-info/METADATA
robotframework_aws-0.0.4.dist-info/WHEEL
robotframework_aws-0.0.4.dist-info/top_level.txt
robotframework_aws-0.0.4.dist-info/RECORD
