Metadata-Version: 2.1
Name: robotframework-aws
Version: 0.0.4
Summary: A python package to test AWS services in Robot Framework
Home-page: https://www.github.com/teaglebuilt/robotframework-aws
Author: Dillan Teagle
Author-email: softwaredeveloper@dillanteagle.me
License: MIT
Platform: UNKNOWN
Classifier: License :: OSI Approved :: MIT License
Classifier: Programming Language :: Python :: 3
Classifier: Programming Language :: Python :: 3.7
Requires-Dist: boto3 (>=1.9.2)
Requires-Dist: robotframework (>=3.1.2)
